pandasdatacube/SPARQL_query.py
pandasdatacube/__init__.py
pandasdatacube/pandasdatacube.py
test/__init__.py
test/test_pandasdatacube.py
pandas_datacube-0.0.4.dist-info/LICENCE.txt
pandas_datacube-0.0.4.dist-info/METADATA
pandas_datacube-0.0.4.dist-info/WHEEL
pandas_datacube-0.0.4.dist-info/top_level.txt
pandas_datacube-0.0.4.dist-info/RECORD
