Metadata-Version: 2.1
Name: pandas-datacube
Version: 0.0.4
Summary: A package allowing to download datacubes into pandas data frames
Home-page: https://github.com/tristansaminadayar/pandas-datacube
Author: Tristan Saminadayar
Author-email: tristan.saminadayar@gmail.com
License: MIT
Classifier: Programming Language :: Python :: 3
Classifier: Programming Language :: Python :: 3.8
Classifier: Programming Language :: Python :: 3.9
Classifier: Programming Language :: Python :: 3.10
Classifier: Programming Language :: Python :: 3.11
Classifier: License :: OSI Approved :: MIT License
Classifier: Operating System :: OS Independent
Classifier: Natural Language :: English
Classifier: Topic :: Database
License-File: LICENCE.txt
Requires-Dist: pandas
Requires-Dist: sparqlwrapper
